mezzanine_other_admin_compat/__init__.py
mezzanine_other_admin_compat/static/mezzanine/js/admin/keywords_field.js
mezzanine_other_admin_compat/templates/admin/base_site.html
mezzanine_other_admin_compat-1.0.2.dist-info/METADATA
mezzanine_other_admin_compat-1.0.2.dist-info/metadata.json
mezzanine_other_admin_compat-1.0.2.dist-info/DESCRIPTION.rst
mezzanine_other_admin_compat-1.0.2.dist-info/top_level.txt
mezzanine_other_admin_compat-1.0.2.dist-info/WHEEL
mezzanine_other_admin_compat-1.0.2.dist-info/RECORD
