Metadata-Version: 2.0
Name: mezzanine-other-admin-compat
Version: 1.0.2
Summary: Django app to provide compatibility with other admin skins/apps when using Mezzanine
Home-page: https://github.com/sjkingo/mezzanine_other_admin_compat
Author: Sam Kingston
Author-email: sam@sjkwi.com.au
License: BSD
Platform: UNKNOWN
